martini_templates/__init__.py
martini_templates/template.mdp.jinja
martini_templates-0.1.0.dist-info/METADATA
martini_templates-0.1.0.dist-info/WHEEL
martini_templates-0.1.0.dist-info/entry_points.txt
martini_templates-0.1.0.dist-info/licenses/LICENSE
martini_templates-0.1.0.dist-info/RECORD
