Metadata-Version: 2.4
Name: martini-templates
Version: 0.1.0
Summary: Create Martini force field templates for GROMACS
Author-email: Alex Moriarty <amoriarty14@gmail.com>
License-Expression: MIT
License-File: LICENSE
Keywords: biomolecules,force field,gromacs,martini,simulation,template
Classifier: Development Status :: 4 - Beta
Classifier: Intended Audience :: Science/Research
Classifier: License :: OSI Approved :: MIT License
Classifier: Programming Language :: Python :: 3
Classifier: Programming Language :: Python :: 3.10
Classifier: Programming Language :: Python :: 3.11
Classifier: Programming Language :: Python :: 3.12
Classifier: Topic :: Scientific/Engineering :: Bio-Informatics
Classifier: Topic :: Scientific/Engineering :: Chemistry
Classifier: Topic :: Scientific/Engineering :: Physics
Requires-Python: >=3.10
Requires-Dist: jinja2>=3.1.6
